sqapi/__init__.py
sqapi/annotate.py
sqapi/api.py
sqapi/helpers.py
sqapi/media.py
sqapi/request.py
sqapi-0.60.dist-info/licenses/LICENSE.txt
sqapi-0.60.dist-info/METADATA
sqapi-0.60.dist-info/WHEEL
sqapi-0.60.dist-info/top_level.txt
sqapi-0.60.dist-info/RECORD
