Metadata-Version: 2.4
Name: sqapi
Version: 0.60
Summary: A python package that simplifies interactions with the SQUIDLE+ API. It can be used to integrate automated labelling from machine learning algorithms and plenty other cool things.
Home-page: https://bitbucket.org/ariell/pysq
Author: Greybits Engineering
License-Expression: MIT
Project-URL: Homepage, https://bitbucket.org/ariell/pysq
Project-URL: Repository, https://bitbucket.org/ariell/pysq
Keywords: SQUIDLE+,API,SQ,Machine Learning
Classifier: Development Status :: 3 - Alpha
Classifier: Intended Audience :: Developers
Classifier: Topic :: Software Development :: Build Tools
Classifier: Programming Language :: Python :: 3
Classifier: Programming Language :: Python :: 3.8
Classifier: Programming Language :: Python :: 3.9
Classifier: Programming Language :: Python :: 3.10
Classifier: Programming Language :: Python :: 3.11
Classifier: Programming Language :: Python :: 3.12
Requires-Python: >=3.8
License-File: LICENSE.txt
Requires-Dist: requests
Requires-Dist: numpy
Requires-Dist: opencv-python
Requires-Dist: tqdm
Requires-Dist: pick
Dynamic: home-page
Dynamic: license-file
